whila/__init__.py
whila-0.1.0.dist-info/LICENSE
whila-0.1.0.dist-info/METADATA
whila-0.1.0.dist-info/WHEEL
whila-0.1.0.dist-info/RECORD
